[
  {
    "uid": "a8bbd1c5492055fee740d4ba13a42911",
    "updateDate": "2026-02-23T00:03:33.0Z",
    "titleText": "JTF News: PBS NewsHour, France 24",
    "mainText": "Olympic cauldrons were extinguished in Milan and Cortina d'Ampezzo, marking the conclusion of the 2026 Winter Olympics.",
    "redirectionUrl": "https://larryseyer.github.io/jtfnews/"
  },
  {
    "uid": "c2206269bcf9ba261c2abd9cc266c69a",
    "updateDate": "2026-02-23T00:02:24.0Z",
    "titleText": "JTF News: Deutsche Welle, NPR",
    "mainText": "Mexican army reports death of drug trafficking organization leader Ismael Oseguera Cervantes.",
    "redirectionUrl": "https://larryseyer.github.io/jtfnews/"
  },
  {
    "uid": "011f59d87b424f2bb1d86cd26ef6530d",
    "updateDate": "2026-02-23T00:01:09.0Z",
    "titleText": "JTF News: NPR, BBC News",
    "mainText": "An armed man was killed after entering a secure perimeter of President Trump's residence, according to the Secret Service.",
    "redirectionUrl": "https://larryseyer.github.io/jtfnews/"
  },
  {
    "uid": "50ca4e3249e3a4569f72e76109e54583",
    "updateDate": "2026-02-22T23:00:47.0Z",
    "titleText": "JTF News: PBS NewsHour, CBC News",
    "mainText": "Olympic cauldrons were extinguished in Milan and Cortina d'Ampezzo, signaling the end of the 2026 Winter Olympics.",
    "redirectionUrl": "https://larryseyer.github.io/jtfnews/"
  },
  {
    "uid": "116ffc31785f94e4da0b7af05a5ce738",
    "updateDate": "2026-02-22T20:00:42.0Z",
    "titleText": "JTF News: Deutsche Welle, NPR",
    "mainText": "The Mexican army killed drug lord Nemesio Oseguera Cervantes, known as 'El Mencho'.",
    "redirectionUrl": "https://larryseyer.github.io/jtfnews/"
  }
]