{
  "date": "2026-02-13",
  "stories": [
    {
      "fact": "Bangladesh's BNP political party won a majority of parliamentary seats in national elections.",
      "source": "Reuters - 9.8* | The Globe and Mail - 8.4*",
      "audio": "../audio/audio_0.mp3"
    },
    {
      "fact": "White House Homeland Security Advisor discussed Minnesota immigration policy following two fatal shootings",
      "source": "BBC News - 9.4* | Associated Press - 9.6* (1/1)",
      "audio": "../audio/audio_1.mp3"
    },
    {
      "fact": "Police report previous interactions with a suspect in a mass shooting in Canada.",
      "source": "BBC News - 9.5* (1/1) | The Guardian - 8.8*",
      "audio": "../audio/audio_2.mp3"
    },
    {
      "fact": "Two individuals accused of using military secrets for financial trading",
      "source": "NPR - 9.2* | Euronews - 8.0*",
      "audio": "../audio/audio_3.mp3"
    },
    {
      "fact": "The U.S. Senate blocked Homeland Security funding legislation.",
      "source": "NPR - 9.3* (1/1) | Reuters - 9.8* (1/1)",
      "audio": "../audio/audio_4.mp3"
    },
    {
      "fact": "Immigration and Customs Enforcement (ICE) agents were arrested in recent months.",
      "source": "NPR - 9.4* (2/2) | Associated Press - 9.7* (2/2)",
      "audio": "../audio/audio_5.mp3"
    },
    {
      "fact": "Police identified 8 people killed in a shooting in Tumbler Ridge, British Columbia.",
      "source": "The Guardian - 8.9* (1/1) | CBC News - 9.1* (1/1)",
      "audio": "../audio/audio_6.mp3"
    },
    {
      "fact": "General Counsel Karen Ruemmler resigned from Goldman Sachs.",
      "source": "Al Jazeera English - 8.5* | Reuters - 9.8* (2/2)",
      "audio": "../audio/audio_7.mp3"
    },
    {
      "fact": "Japan reported seizing a Chinese vessel.",
      "source": "Al Jazeera English - 8.7* (1/1) | BBC News - 9.5* (2/2)",
      "audio": "../audio/audio_8.mp3"
    },
    {
      "fact": "Environmental Protection Agency revokes scientific finding related to climate change policy",
      "source": "Al Jazeera English - 8.8* (2/2) | Associated Press - 9.7* (3/3)",
      "audio": "../audio/audio_9.mp3"
    },
    {
      "fact": "France's Laurane Miradoli won silver medal in Women's Super-G at Milano-Cortina Winter Olympics",
      "source": "France 24 - 8.7* (1/1) | Associated Press - 9.8* (4/4)",
      "audio": "../audio/audio_10.mp3"
    },
    {
      "fact": "President Trump eliminated legal foundation for climate regulations",
      "source": "France 24 - 8.9* (2/2) | BBC News - 9.6* (3/3)",
      "audio": "../audio/audio_11.mp3"
    },
    {
      "fact": "Indian unions and farmers conducted a nationwide strike in response to an interim trade deal with the United States",
      "source": "France 24 - 9.0* (3/3) | Associated Press - 9.8* (5/5)",
      "audio": "../audio/audio_12.mp3"
    },
    {
      "fact": "President Cyril Ramaphosa announced military deployment to address criminal activity in South Africa",
      "source": "Deutsche Welle - 8.7* | Al Jazeera English - 8.9* (3/3)",
      "audio": "../audio/audio_13.mp3"
    },
    {
      "fact": "The U.S. government stated that European nations should take the lead on defense in NATO.",
      "source": "Sky News - 8.2* | Al Jazeera English - 9.1* (4/4)",
      "audio": "../audio/audio_14.mp3"
    },
    {
      "fact": "Ukrainian athlete Vladyslav Heraskevych will not compete in the Winter Olympics",
      "source": "Sky News - 8.4* (1/1) | Associated Press - 9.8* (6/6)",
      "audio": "../audio/audio_15.mp3"
    },
    {
      "fact": "NATO leaders will gather for the Munich Security Conference.",
      "source": "PBS NewsHour - 9.2* (1/1) | France 24 - 9.2* (4/4)",
      "audio": "../audio/audio_16.mp3"
    },
    {
      "fact": "Ongoing conflict between Russia and Ukraine continues into its 1,450th day.",
      "source": "PBS NewsHour - 9.3* (2/2) | Al Jazeera English - 9.2* (5/5)",
      "audio": "../audio/audio_17.mp3"
    },
    {
      "fact": "A shooting in Canada resulted in 9 deaths and 25 injuries at a school and home.",
      "source": "Associated Press - 9.9* (7/7) | The Guardian - 9.0* (2/2)",
      "audio": "../audio/audio_18.mp3"
    },
    {
      "fact": "Ukrainian President Volodymyr Zelenskiy stated that Ukraine has backed US peace proposals.",
      "source": "Reuters - 9.9* (3/3) | The Straits Times - 7.6*",
      "audio": "../audio/audio_19.mp3"
    },
    {
      "fact": "Portugal approved restrictions on social media access for children.",
      "source": "Euronews - 8.2* (1/1) | The Straits Times - 7.8* (1/1)",
      "audio": "../audio/audio_20.mp3"
    },
    {
      "fact": "A shooting at South Carolina State University resulted in two deaths and one injury.",
      "source": "Reuters - 9.9* (4/4) | The Straits Times - 8.1* (2/2)",
      "audio": "../audio/audio_21.mp3"
    },
    {
      "fact": "Turkey detained 16 individuals in connection with OnlyFans activity and seized $6.9 million in assets.",
      "source": "Reuters - 9.9* (5/5) | The Straits Times - 8.3* (3/3)",
      "audio": "../audio/audio_22.mp3"
    },
    {
      "fact": "One person died and hundreds of thousands lost power in France during Storm Nils.",
      "source": "Deutsche Welle - 8.8* (1/1) | France 24 - 9.3* (5/5)",
      "audio": "../audio/audio_23.mp3"
    },
    {
      "fact": "The FBI released a description of a suspect in the Nancy Guthrie kidnapping.",
      "source": "BBC News - 9.6* (4/4) | The Straits Times - 8.6* (4/4)",
      "audio": "../audio/audio_24.mp3"
    },
    {
      "fact": "French astronaut Sophie Adenot and crew launched to the International Space Station.",
      "source": "France 24 - 9.4* (6/6) | NPR - 9.4* (3/3)",
      "audio": "../audio/audio_25.mp3"
    },
    {
      "fact": "Ukraine expects final International Monetary Fund deal approval in coming weeks.",
      "source": "Reuters - 9.9* (6/6) | The Straits Times - 8.8* (5/5)",
      "audio": "../audio/audio_26.mp3"
    },
    {
      "fact": "A court ruled the UK's decision to ban Palestine Action as a terrorist group was unlawful.",
      "source": "NPR - 9.5* (4/4) | France 24 - 9.6* (7/7)",
      "audio": "../audio/audio_27.mp3"
    },
    {
      "fact": "More than 5,000 ISIL detainees were transferred from Syria according to the Iraqi ministry.",
      "source": "Al Jazeera English - 9.2* (5/5) | The Straits Times - 9.0* (6/6)",
      "audio": "../audio/audio_28.mp3"
    },
    {
      "fact": "A second U.S. aircraft carrier is heading to the Middle East, according to U.S. media reports.",
      "source": "The Globe and Mail - 8.6* (1/1) | Reuters - 9.9* (7/7)",
      "audio": "../audio/audio_29.mp3"
    },
    {
      "fact": "Police identified 8 people killed in a shooting in Tumbler Ridge, British Columbia.",
      "source": "ABC News Australia - 9.1* (1/1) | CBC News - 9.2* (2/2)",
      "audio": "../audio/audio_30.mp3"
    },
    {
      "fact": "One person was killed and six were injured in a Russian air attack on a port in Ukraine's Odesa region, according to a deputy prime minister.",
      "source": "Euronews - 8.4* (2/2) | The Straits Times - 9.3* (7/7)",
      "audio": "../audio/audio_31.mp3"
    },
    {
      "fact": "President Emmanuel Macron called for stronger measures against antisemitism in France.",
      "source": "The Straits Times - 9.5* (8/8) | France 24 - 9.7* (8/8)",
      "audio": "../audio/audio_32.mp3"
    },
    {
      "fact": "German Chancellor called on the US and Europe to repair and revive trans-Atlantic trust.",
      "source": "The Globe and Mail - 8.7* (2/2) | Associated Press - 9.9* (8/8)",
      "audio": "../audio/audio_33.mp3"
    },
    {
      "fact": "Three skiers died in an avalanche at Val d'Is\u00e8re resort in France.",
      "source": "Deutsche Welle - 9.0* (2/2) | The Straits Times - 9.8* (9/9)",
      "audio": "../audio/audio_34.mp3"
    },
    {
      "fact": "The Trump administration filed a lawsuit against Harvard University regarding an admissions probe.",
      "source": "Reuters - 10.0* (8/8) | The Globe and Mail - 8.9* (3/3)",
      "audio": "../audio/audio_35.mp3"
    },
    {
      "fact": "The United Nations reports 6,000 deaths in a Sudanese city over three days.",
      "source": "BBC News - 9.7* (5/5) | Al Jazeera English - 9.4* (6/6)",
      "audio": "../audio/audio_36.mp3"
    },
    {
      "fact": "Russia and Ukraine are scheduled to hold talks in Geneva next week.",
      "source": "Al Jazeera English - 9.6* (7/7) | The Globe and Mail - 9.0* (4/4)",
      "audio": "../audio/audio_37.mp3"
    },
    {
      "fact": "President Trump pardoned 5 former NFL players convicted of offenses ranging from perjury to drug trafficking.",
      "source": "Al Jazeera English - 9.7* (8/8) | NPR - 9.6* (5/5)",
      "audio": "../audio/audio_38.mp3"
    },
    {
      "fact": "Paris police fired on a knife attacker at the Arc de Triomphe.",
      "source": "Deutsche Welle - 9.1* (3/3) | France 24 - 9.9* (9/9)",
      "audio": "../audio/audio_39.mp3"
    },
    {
      "fact": "Trump stated he will visit Venezuela.",
      "source": "The Straits Times - 10.0 (10/10) | EFE News Agency - 8.8*",
      "audio": "../audio/audio_40.mp3"
    },
    {
      "fact": "Senators urged President Trump to eliminate social media vetting for foreign tourists.",
      "source": "Hindustan Times - 7.4* | The Straits Times - 10.0 (11/11)",
      "audio": "../audio/audio_41.mp3"
    }
  ]
}